[
  {
    "time": "2026-06-22T19:25:17",
    "action": "select",
    "equity_last": 1000000,
    "query": "A股主板非ST 今日涨幅4.5%到5.3% 今日量比大于0.8 收盘价接近最高价 弱转强候选",
    "picks": [],
    "raw_count": 9
  },
  {
    "time": "2026-06-22T19:25:39",
    "action": "select",
    "equity_last": 1000000,
    "query": "A股主板非ST 今日涨幅4.5%到5.3% 今日量比大于0.8 收盘价接近最高价 弱转强候选",
    "picks": [],
    "raw_count": 9
  },
  {
    "time": "2026-06-22T19:25:39",
    "action": "execute_skip",
    "equity_last": 1000000,
    "total_assets": 1070108.604,
    "avail_balance": 177757.404,
    "sells": [],
    "buys": []
  },
  {
    "time": "2026-06-22T19:28:31",
    "action": "select",
    "equity_last": 1070108.604,
    "query": "A股主板非ST 今日涨幅4.5%到5.3% 今日量比大于0.8 收盘价接近最高价 弱转强候选",
    "picks": [
      {
        "code": "601168",
        "name": "西部矿业",
        "pct": 5.1,
        "vol_ratio": 1.14,
        "price": 33.37
      },
      {
        "code": "002716",
        "name": "湖南白银",
        "pct": 5.03,
        "vol_ratio": 1.06,
        "price": 9.6
      },
      {
        "code": "605378",
        "name": "野马电池",
        "pct": 4.93,
        "vol_ratio": 2.46,
        "price": 18.1
      }
    ],
    "raw_count": 9
  },
  {
    "time": "2026-06-22T14:45:59",
    "action": "select",
    "equity_last": 1070108.604,
    "query": "A股主板非ST 今日涨幅4.5%到5.3% 今日量比大于0.8 收盘价接近最高价 弱转强候选",
    "picks": [
      {
        "code": "601168",
        "name": "西部矿业",
        "pct": 5.1,
        "vol_ratio": 1.14,
        "price": 33.37
      },
      {
        "code": "002716",
        "name": "湖南白银",
        "pct": 5.03,
        "vol_ratio": 1.06,
        "price": 9.6
      },
      {
        "code": "605378",
        "name": "野马电池",
        "pct": 4.93,
        "vol_ratio": 2.46,
        "price": 18.1
      }
    ],
    "raw_count": 9
  }
]